[{"tag": "T-Shirt", "count": 1450}, {"tag": "Shirt", "count": 3463}, {"tag": "Dress", "count": 547}, {"tag": "Saree", "count": 145}, {"tag": "Jeans", "count": 1100}, {"tag": "Kurta", "count": 892}, {"tag": "Shoes", "count": 272}, {"tag": "Shorts", "count": 107}, {"tag": "Skirt", "count": 56}, {"tag": "Jacket", "count": 352}, {"tag": "Sweater", "count": 183}, {"tag": "Sweatshirt", "count": 310}, {"tag": "Trousers", "count": 418}, {"tag": "Top", "count": 661}, {"tag": "Bag", "count": 294}, {"tag": "Wallet", "count": 64}, {"tag": "Watch", "count": 302}]
